arbory/__init__.py
arbory/__version__.py
arbory/config_spec.py
arbory/const.py
arbory/core.py
arbory/subcommands/__init__.py
arbory/subcommands/config.py
arbory/subcommands/tree.py
arbory-0.0.5.dist-info/LICENSE
arbory-0.0.5.dist-info/METADATA
arbory-0.0.5.dist-info/WHEEL
arbory-0.0.5.dist-info/entry_points.txt
arbory-0.0.5.dist-info/top_level.txt
arbory-0.0.5.dist-info/RECORD
